thunderstruck_bms/bms.py
thunderstruck_bms/test_bmsCellReportMessage.py
thunderstruck_bms/test_bmsStatusMessage.py
thunderstruck_bms/test_bmsTemperatureStatus.py
thunderstruck_bms-1.0.2.dist-info/LICENSE
thunderstruck_bms-1.0.2.dist-info/METADATA
thunderstruck_bms-1.0.2.dist-info/WHEEL
thunderstruck_bms-1.0.2.dist-info/top_level.txt
thunderstruck_bms-1.0.2.dist-info/RECORD
