Metadata-Version: 2.1
Name: thunderstruck-bms
Version: 1.0.2
Summary: Thunderstruck BMS Controller
Author-email: Ruslan Babych <ruslan.babych@digitwolf.com>
License: Apache License
Project-URL: Homepage, https://github.com/aranji/thunderstruck_bms
Keywords: thunderstruck,bms
Classifier: License :: OSI Approved :: Apache Software License
Classifier: Programming Language :: Python
Classifier: Programming Language :: Python :: 3
Requires-Python: >=3.6
License-File: LICENSE
Requires-Dist: python-can
Requires-Dist: asyncio
